[
  {
    "full_name": "typeorm/typeorm",
    "stargazers_count": 36089,
    "open_issues_count": 527,
    "forks_count": 6466
  },
  {
    "full_name": "inthaider/web_scraper-ircc_citizenship_portal",
    "stargazers_count": 2,
    "open_issues_count": 0,
    "forks_count": 0
  },
  {
    "full_name": "es-tooling/module-replacements",
    "stargazers_count": 732,
    "open_issues_count": 61,
    "forks_count": 48
  },
  {
    "full_name": "coturn/coturn",
    "stargazers_count": 13266,
    "open_issues_count": 373,
    "forks_count": 2186
  },
  {
    "full_name": "webrtc/samples",
    "stargazers_count": 14535,
    "open_issues_count": 43,
    "forks_count": 5748
  },
  {
    "full_name": "alan2207/bulletproof-react",
    "stargazers_count": 33677,
    "open_issues_count": 49,
    "forks_count": 3039
  },
  {
    "full_name": "DeterminateSystems/nix-installer",
    "stargazers_count": 3276,
    "open_issues_count": 393,
    "forks_count": 100
  },
  {
    "full_name": "sorrycc/awesome-javascript",
    "stargazers_count": 34782,
    "open_issues_count": 25,
    "forks_count": 4497
  },
  {
    "full_name": "vinta/awesome-python",
    "stargazers_count": 272036,
    "open_issues_count": 519,
    "forks_count": 26844
  },
  {
    "full_name": "OyedejiEnoch/RunOrder-Delivery",
    "stargazers_count": 1,
    "open_issues_count": 0,
    "forks_count": 0
  },
  {
    "full_name": "cassidoo/talks",
    "stargazers_count": 695,
    "open_issues_count": 0,
    "forks_count": 56
  },
  {
    "full_name": "romkatv/powerlevel10k",
    "stargazers_count": 51804,
    "open_issues_count": 135,
    "forks_count": 2375
  },
  {
    "full_name": "ohmyzsh/ohmyzsh",
    "stargazers_count": 183081,
    "open_issues_count": 530,
    "forks_count": 26289
  },
  {
    "full_name": "lirantal/awesome-nodejs-security",
    "stargazers_count": 2959,
    "open_issues_count": 0,
    "forks_count": 267
  },
  {
    "full_name": "ByteByteGoHq/system-design-101",
    "stargazers_count": 78247,
    "open_issues_count": 54,
    "forks_count": 8522
  },
  {
    "full_name": "Agenta-AI/agenta",
    "stargazers_count": 3457,
    "open_issues_count": 98,
    "forks_count": 408
  },
  {
    "full_name": "RecipeUI/RecipeUI",
    "stargazers_count": 1338,
    "open_issues_count": 22,
    "forks_count": 41
  },
  {
    "full_name": "alfateam/orange-orm",
    "stargazers_count": 919,
    "open_issues_count": 8,
    "forks_count": 19
  },
  {
    "full_name": "DovAmir/awesome-design-patterns",
    "stargazers_count": 44982,
    "open_issues_count": 20,
    "forks_count": 3155
  },
  {
    "full_name": "binhnguyennus/awesome-scalability",
    "stargazers_count": 66993,
    "open_issues_count": 18,
    "forks_count": 6702
  },
  {
    "full_name": "MunGell/awesome-for-beginners",
    "stargazers_count": 80227,
    "open_issues_count": 59,
    "forks_count": 7612
  },
  {
    "full_name": "sindresorhus/awesome-nodejs",
    "stargazers_count": 63921,
    "open_issues_count": 24,
    "forks_count": 6121
  },
  {
    "full_name": "nodejs/node",
    "stargazers_count": 114533,
    "open_issues_count": 2416,
    "forks_count": 33931
  },
  {
    "full_name": "weagle08/sequelizejs-decorators",
    "stargazers_count": 22,
    "open_issues_count": 2,
    "forks_count": 3
  },
  {
    "full_name": "OWASP/CheatSheetSeries",
    "stargazers_count": 30810,
    "open_issues_count": 60,
    "forks_count": 4301
  },
  {
    "full_name": "imgly/background-removal-js",
    "stargazers_count": 6839,
    "open_issues_count": 66,
    "forks_count": 442
  },
  {
    "full_name": "Infisical/infisical",
    "stargazers_count": 23804,
    "open_issues_count": 552,
    "forks_count": 1599
  },
  {
    "full_name": "fern-api/fern",
    "stargazers_count": 3420,
    "open_issues_count": 413,
    "forks_count": 268
  },
  {
    "full_name": "railwayapp-templates/expressjs-prisma",
    "stargazers_count": 11,
    "open_issues_count": 0,
    "forks_count": 13
  },
  {
    "full_name": "ljlm0402/typescript-express-starter",
    "stargazers_count": 2868,
    "open_issues_count": 48,
    "forks_count": 443
  }
]